.gitignore
.pre-commit-config.yaml
.pylintrc
README.rst
pathy.py
run_tests
setup.py
docs/Makefile
docs/api.rst
docs/capabilities.rst
docs/conf.py
docs/index.rst
docs/intro.rst
docs/project_structure.rst
subpop/__init__.py
subpop/config.py
subpop/hub.py
subpop/pkg.py
subpop/util.py
subpop.egg-info/PKG-INFO
subpop.egg-info/SOURCES.txt
subpop.egg-info/dependency_links.txt
subpop.egg-info/requires.txt
subpop.egg-info/top_level.txt
tests/test_add_to_hub.py
tests/test_import_1.py
tests/test_import_2.py
tests/test_import_env.py
tests/test_import_iter.py
tests/test_import_key_error.py
tests/test_import_model_init.py
tests/test_import_syntax_error.py
tests/plugin_project_env_dir/subpop.yaml
tests/plugin_project_env_dir/subsystems/model_sub/first.py
tests/plugin_project_env_dir/subsystems/mysub/foo.py
tests/plugin_project_env_dir/subsystems/mysub/key_error.py
tests/plugin_project_env_dir/subsystems/mysub/syntax_error.py
tests/plugin_test_dir/org.funtoo.powerbus/baselevel.py
tests/plugin_test_dir/org.funtoo.powerbus/system/bar.py
tests/plugin_test_dir/org.funtoo.powerbus/system/foo.py