Metadata-Version: 2.1
Name: subpop
Version: 2.0.0
Summary: A gentle evolution of the POP paradigm.
Home-page: https://code.funtoo.org/bitbucket/users/drobbins/repos/subpop/browse
Author: Daniel Robbins
Author-email: drobbins@funtoo.org
License: UNKNOWN
Platform: UNKNOWN
Classifier: Programming Language :: Python :: 3
Classifier: License :: OSI Approved :: Apache Software License
Classifier: Operating System :: POSIX :: Linux
Requires-Python: >=3.7
